MANIFEST.in
README.md
setup.py
poeem_1_2_1.egg-info/PKG-INFO
poeem_1_2_1.egg-info/SOURCES.txt
poeem_1_2_1.egg-info/dependency_links.txt
poeem_1_2_1.egg-info/requires.txt
poeem_1_2_1.egg-info/top_level.txt
src/__init__.py
src/ops/bin/__init__.py
src/ops/bin/clustering_op.so
src/ops/bin/clustering_raw_op.so
src/ops/bin/combinatorial_op.so
src/ops/bin/pqknn_dataset_op.so
src/ops/bin/rec_dataset_op.so
src/ops/bin/search_op.so
src/ops/bin/tokenizer_op.so
src/ops/cpp/clustering_op.cc
src/ops/cpp/clustering_raw_op.cc
src/ops/cpp/clustering_raw_op.cc~
src/ops/cpp/combinatorial_op.cc
src/ops/cpp/pqknn_dataset_op.cc
src/ops/cpp/pqknn_dataset_op.h
src/ops/cpp/rec_dataset_op.cc
src/ops/cpp/search_op.cc
src/ops/cpp/tokenizer_op.cc
src/ops/cpp/vector_util.h
src/ops/python/__init__.py
src/ops/python/clustering.py
src/ops/python/combinatorics.py
src/ops/python/encode.py
src/ops/python/indexing.py
src/ops/python/pqknn_dataset.py
src/ops/python/rec_dataset.py
src/ops/python/search.py
src/ops/python/tokenizer.py
src/python/__init__.py
src/python/embedding.py