Metadata-Version: 2.1
Name: poeem-1-2-1
Version: 1.2.1
Summary: A library for jointly training embedding retrieval model and product quantization based index
Home-page: UNKNOWN
Author: JD.com
Author-email: wenyun.yang@jd.com
License: MIT
Platform: UNKNOWN
Classifier: License :: OSI Approved :: MIT License
Classifier: Programming Language :: Python :: 3
Classifier: Programming Language :: Python :: 3.6
